LICENSE
README.md
setup.py
cornelius/__init__.py
cornelius/cursor.py
cornelius/exceptions.py
cornelius/keyboard.py
cornelius/structs.py
cornelius.egg-info/PKG-INFO
cornelius.egg-info/SOURCES.txt
cornelius.egg-info/dependency_links.txt
cornelius.egg-info/top_level.txt