Metadata-Version: 2.1
Name: cornelius
Version: 0.0.3
Summary: Python mouse and keyboard input control in a simple way.
Home-page: https://github.com/manucabral/cornelius
Author: Manuel Cabral
Author-email: cabral.manuel@yandex.com
License: GPLv3
Keywords: mouseinput,keyboardinput,input,win32,inputcontrol
Platform: UNKNOWN
Classifier: Intended Audience :: Developers
Classifier: Topic :: Software Development :: Build Tools
Classifier: Programming Language :: Python :: 3
Classifier: Operating System :: Microsoft :: Windows
Requires-Python: >= 3.2
License-File: LICENSE
